upyuns3client/__init__.py
upyuns3client/upyuns3client.py
upyuns3client-0.1.4.dist-info/METADATA
upyuns3client-0.1.4.dist-info/WHEEL
upyuns3client-0.1.4.dist-info/top_level.txt
upyuns3client-0.1.4.dist-info/RECORD
