Metadata-Version: 2.1
Name: upyuns3client
Version: 0.1.4
Summary: UpYun Storage SDK for Python S3 Support
Home-page: https://github.com/evansuner/upyuns3client
Author: Evan
Author-email: zhidong.s@outlook.com
License: License :: OSI Approved :: MIT License
Keywords: upyun,python,sdk,s3
Classifier: Development Status :: 5 - Production/Stable
Classifier: Intended Audience :: Developers
Classifier: License :: OSI Approved :: MIT License
Classifier: Operating System :: OS Independent
Classifier: Programming Language :: Python
Classifier: Programming Language :: Python :: 3.7
Classifier: Programming Language :: Python :: 3.8
Classifier: Programming Language :: Python :: 3.9
Requires-Dist: boto3 ==1.28.30
Requires-Dist: python-dotenv ==1.0.0
